pyvultr/__init__.py
pyvultr/base_api.py
pyvultr/cli.py
pyvultr/exception.py
pyvultr/main.py
pyvultr/utils/__init__.py
pyvultr/utils/box.py
pyvultr/utils/pagination.py
pyvultr/v2/__init__.py
pyvultr/v2/account.py
pyvultr/v2/application.py
pyvultr/v2/backup.py
pyvultr/v2/bare_metal.py
pyvultr/v2/base.py
pyvultr/v2/billing.py
pyvultr/v2/block_storage.py
pyvultr/v2/dns.py
pyvultr/v2/enums.py
pyvultr/v2/firewall.py
pyvultr/v2/instance.py
pyvultr/v2/iso.py
pyvultr/v2/kubernetes.py
pyvultr/v2/load_balance.py
pyvultr/v2/object_storage.py
pyvultr/v2/operating_system.py
pyvultr/v2/plan.py
pyvultr/v2/private_network.py
pyvultr/v2/region.py
pyvultr/v2/reserved_ip.py
pyvultr/v2/snapshot.py
pyvultr/v2/ssh_key.py
pyvultr/v2/startup_script.py
pyvultr/v2/user.py
pyvultr-0.1.5.dist-info/entry_points.txt
pyvultr-0.1.5.dist-info/LICENSE
pyvultr-0.1.5.dist-info/WHEEL
pyvultr-0.1.5.dist-info/METADATA
pyvultr-0.1.5.dist-info/RECORD
