Metadata-Version: 2.1
Name: pyvultr
Version: 0.1.5
Summary: Python library for Vultr API
Home-page: https://github.com/luxiaba/pyvultr
License: MIT
Keywords: vultri,api,cloud,vultr-api
Author: fishermanadg
Author-email: fishermanadg@gmail.com
Requires-Python: >=3.6.2,<4.0.0
Classifier: Development Status :: 5 - Production/Stable
Classifier: Intended Audience :: Developers
Classifier: License :: OSI Approved :: MIT License
Classifier: Operating System :: MacOS
Classifier: Operating System :: POSIX
Classifier: Operating System :: POSIX :: Linux
Classifier: Programming Language :: Python
Classifier: Programming Language :: Python :: 3
Classifier: Programming Language :: Python :: 3.10
Classifier: Programming Language :: Python :: 3.6
Classifier: Programming Language :: Python :: 3.7
Classifier: Programming Language :: Python :: 3.8
Classifier: Programming Language :: Python :: 3.9
Classifier: Programming Language :: Python :: Implementation :: CPython
Classifier: Programming Language :: Python :: Implementation :: PyPy
Classifier: Topic :: Software Development :: Libraries
Classifier: Topic :: Software Development :: Libraries :: Python Modules
Classifier: Topic :: Utilities
Requires-Dist: Pygments (>=2.10.0,<3.0.0)
Requires-Dist: dacite (>=1.6.0,<2.0.0)
Requires-Dist: fire (>=0.4.0,<0.5.0)
Requires-Dist: requests (>=2.26.0,<3.0.0)
Project-URL: Repository, https://github.com/luxiaba/pyvultr.git
